LICENSE
MANIFEST.in
README.md
setup.py
nose_django_querycount.egg-info/PKG-INFO
nose_django_querycount.egg-info/SOURCES.txt
nose_django_querycount.egg-info/dependency_links.txt
nose_django_querycount.egg-info/entry_points.txt
nose_django_querycount.egg-info/not-zip-safe
nose_django_querycount.egg-info/requires.txt
nose_django_querycount.egg-info/top_level.txt
nosequerycount/__init__.py
nosequerycount/plugin.py
nosequerycount/utils.py