Metadata-Version: 1.0
Name: nose-django-querycount
Version: 0.2
Summary: Nose plugin for counting queries in Django tests
Home-page: https://github.com/dgladkov/nose-django-querycount
Author: Dmitry Gladkov
Author-email: dmitry.gladkov@gmail.com
License: UNKNOWN
Keywords: test unittest nosetests nose plugin django queries querycount
Platform: UNKNOWN
Classifier: Development Status :: 3 - Alpha
Classifier: Environment :: Console
Classifier: Framework :: Django
Classifier: Intended Audience :: Developers
Classifier: Operating System :: OS Independent
Classifier: Programming Language :: Python
Classifier: Topic :: Software Development
